pyskip.py
pyskip-0.9.0.dist-info/DESCRIPTION.rst
pyskip-0.9.0.dist-info/METADATA
pyskip-0.9.0.dist-info/pydist.json
pyskip-0.9.0.dist-info/RECORD
pyskip-0.9.0.dist-info/top_level.txt
pyskip-0.9.0.dist-info/WHEEL
